shacl2code/__init__.py
shacl2code/__main__.py
shacl2code/context.py
shacl2code/main.py
shacl2code/model.py
shacl2code/urlcontext.py
shacl2code/version.py
shacl2code/lang/__init__.py
shacl2code/lang/common.py
shacl2code/lang/cpp.py
shacl2code/lang/golang.py
shacl2code/lang/jinja.py
shacl2code/lang/jsonschema.py
shacl2code/lang/lang.py
shacl2code/lang/python.py
shacl2code/lang/sources/cpp/json.hpp
shacl2code/lang/templates/jsonschema.j2
shacl2code/lang/templates/python.j2
shacl2code/lang/templates/cpp/Doxyfile.j2
shacl2code/lang/templates/cpp/Makefile.j2
shacl2code/lang/templates/cpp/api.hpp.j2
shacl2code/lang/templates/cpp/datetime.cpp.j2
shacl2code/lang/templates/cpp/datetime.hpp.j2
shacl2code/lang/templates/cpp/decode.cpp.j2
shacl2code/lang/templates/cpp/decode.hpp.j2
shacl2code/lang/templates/cpp/encode.cpp.j2
shacl2code/lang/templates/cpp/encode.hpp.j2
shacl2code/lang/templates/cpp/errorhandler.cpp.j2
shacl2code/lang/templates/cpp/errorhandler.hpp.j2
shacl2code/lang/templates/cpp/exceptions.hpp.j2
shacl2code/lang/templates/cpp/extensible.cpp.j2
shacl2code/lang/templates/cpp/extensible.hpp.j2
shacl2code/lang/templates/cpp/header.j2
shacl2code/lang/templates/cpp/jsonld-header.j2
shacl2code/lang/templates/cpp/jsonld-source.j2
shacl2code/lang/templates/cpp/link.cpp.j2
shacl2code/lang/templates/cpp/link.hpp.j2
shacl2code/lang/templates/cpp/namedindividual.cpp.j2
shacl2code/lang/templates/cpp/namedindividual.hpp.j2
shacl2code/lang/templates/cpp/object.cpp.j2
shacl2code/lang/templates/cpp/object.hpp.j2
shacl2code/lang/templates/cpp/objectpath.cpp.j2
shacl2code/lang/templates/cpp/objectpath.hpp.j2
shacl2code/lang/templates/cpp/objectset.cpp.j2
shacl2code/lang/templates/cpp/objectset.hpp.j2
shacl2code/lang/templates/cpp/pkgconfig.pc.j2
shacl2code/lang/templates/cpp/prop.hpp.j2
shacl2code/lang/templates/cpp/property.cpp.j2
shacl2code/lang/templates/cpp/property.hpp.j2
shacl2code/lang/templates/cpp/propertyvalue.cpp.j2
shacl2code/lang/templates/cpp/propertyvalue.hpp.j2
shacl2code-0.0.24.dist-info/METADATA
shacl2code-0.0.24.dist-info/WHEEL
shacl2code-0.0.24.dist-info/entry_points.txt
shacl2code-0.0.24.dist-info/licenses/LICENSE
shacl2code-0.0.24.dist-info/RECORD
