Metadata-Version: 2.4
Name: shacl2code
Version: 0.0.24
Summary: Convert SHACL model file to code bindings
Project-URL: Homepage, https://github.com/JPEWdev/shacl2code
Project-URL: Repository, https://github.com/JPEWdev/shacl2code.git
Project-URL: Issues, https://github.com/JPEWdev/shacl2code/issues
Author-email: Joshua Watt <JPEWhacker@gmail.com>
License-Expression: MIT
License-File: LICENSE
Classifier: Development Status :: 4 - Beta
Classifier: Intended Audience :: Developers
Classifier: Programming Language :: Python :: 3
Classifier: Programming Language :: Python :: 3.8
Classifier: Programming Language :: Python :: 3.9
Classifier: Programming Language :: Python :: 3.10
Classifier: Programming Language :: Python :: 3.11
Classifier: Programming Language :: Python :: 3.12
Classifier: Topic :: Software Development :: Build Tools
Requires-Python: >=3.8
Requires-Dist: jinja2>=3.1.2
Requires-Dist: rdflib>=7.0.0
Provides-Extra: dev
Requires-Dist: flake8>=7.0.0; extra == 'dev'
Requires-Dist: jsonschema>=4.21.1; extra == 'dev'
Requires-Dist: mypy>=1.14.1; extra == 'dev'
Requires-Dist: pyrefly>=0.28.1; extra == 'dev'
Requires-Dist: pyright>=1.1.403; extra == 'dev'
Requires-Dist: pyshacl>=0.25.0; extra == 'dev'
Requires-Dist: pytest-cov>=4.1; extra == 'dev'
Requires-Dist: pytest>=7.4; extra == 'dev'
